MANIFEST.in
README.rst
setup.py
datastore/__init__.py
datastore/settings.py
datastore/test_settings.py
datastore/urls.py
datastore/wsgi.py
facebook_datastore/__init__.py
facebook_datastore/engines.py
facebook_datastore/factories.py
facebook_datastore/graph_api.py
facebook_datastore/models.py
facebook_datastore/parser.py
facebook_datastore/tests.py
facebook_datastore.egg-info/PKG-INFO
facebook_datastore.egg-info/SOURCES.txt
facebook_datastore.egg-info/dependency_links.txt
facebook_datastore.egg-info/requires.txt
facebook_datastore.egg-info/top_level.txt
facebook_datastore/migrations/0001_initial.py
facebook_datastore/migrations/0002_auto_20150212_1518.py
facebook_datastore/migrations/0003_auto_20150602_1017.py
facebook_datastore/migrations/0004_auto_20150602_1018.py
facebook_datastore/migrations/__init__.py
facebook_datastore/south_migrations/0001_initial.py
facebook_datastore/south_migrations/0002_auto__add_facebookuserlike__add_unique_facebookuserlike_user_facebook_.py
facebook_datastore/south_migrations/0003_auto__chg_field_facebookuserlike_name.py
facebook_datastore/south_migrations/0004_auto__add_facebookfriend__add_unique_facebookfriend_user_friend_facebo.py
facebook_datastore/south_migrations/0005_auto__add_field_facebookuserprofile_age_range_min__add_field_facebooku.py
facebook_datastore/south_migrations/0006_auto__add_field_facebookuserprofile_uses_ios__add_field_facebookuserpr.py
facebook_datastore/south_migrations/__init__.py