Metadata-Version: 1.0
Name: facebook-datastore
Version: 3.1.2
Summary: Facebook Datastore
Home-page: UNKNOWN
Author: Tomasz Wysocki
Author-email: tomasz@wysocki.info
License: UNKNOWN
Platform: UNKNOWN
